{"hash":"e72f2618f87140dda86b5f5d431489353d30d6bb","data":{"posts":{"totalCount":10,"pageInfo":{"totalPages":4,"currentPage":4},"edges":[{"node":{"id":"a42b8bcc7bf15f7796de02de7ae64711","title":"Jeffsum, a Jeff Goldblum movie lines text placeholder generator","timeToRead":1,"datetime":"2018-02-24 18:23:28","content":"<p><a href=\"https://radeau.github.io/blog/\" target=\"_blank\" rel=\"nofollow noopener noreferrer\">Go back Home!!</a></p>\n","excerpt":"Checkmate... Remind me to thank John for a lovely weekend. You know what? It is beets. I've crashed into a beet truck. Jaguar shark! So tell me - does it really exist? Is this my espresso machine? Wh-what is-h-how did you get my espresso machine? What do they got in there? King Kong? [...]","description":"A little text placeholder generator of Jeff Goldblum awesomeness.","path":"/jeffsum-a-jeff-goldblum-movie-lines-text-placeholder-generator/","cover":null,"tags":[{"id":"archived","title":"archived","path":"/tag/archived/"}],"author":{"id":"kevin-rad","title":"kevin-rad","path":"/author/kevin-rad/"}}}]}},"context":{}}